selfcord/__init__.py
selfcord/__main__.py
selfcord/abc.py
selfcord/activity.py
selfcord/affinity.py
selfcord/appinfo.py
selfcord/application.py
selfcord/asset.py
selfcord/audit_logs.py
selfcord/automod.py
selfcord/backoff.py
selfcord/billing.py
selfcord/calls.py
selfcord/channel.py
selfcord/client.py
selfcord/colour.py
selfcord/commands.py
selfcord/components.py
selfcord/connections.py
selfcord/context_managers.py
selfcord/directory.py
selfcord/embeds.py
selfcord/emoji.py
selfcord/entitlements.py
selfcord/enums.py
selfcord/errors.py
selfcord/experiment.py
selfcord/file.py
selfcord/flags.py
selfcord/gateway.py
selfcord/guild.py
selfcord/guild_folder.py
selfcord/guild_premium.py
selfcord/handlers.py
selfcord/http.py
selfcord/integrations.py
selfcord/interactions.py
selfcord/invite.py
selfcord/library.py
selfcord/member.py
selfcord/mentions.py
selfcord/message.py
selfcord/metadata.py
selfcord/mixins.py
selfcord/modal.py
selfcord/oauth2.py
selfcord/object.py
selfcord/oggparse.py
selfcord/opus.py
selfcord/partial_emoji.py
selfcord/payments.py
selfcord/permissions.py
selfcord/player.py
selfcord/poll.py
selfcord/profile.py
selfcord/promotions.py
selfcord/py.typed
selfcord/raw_models.py
selfcord/reaction.py
selfcord/read_state.py
selfcord/relationship.py
selfcord/role.py
selfcord/scheduled_event.py
selfcord/settings.py
selfcord/stage_instance.py
selfcord/state.py
selfcord/sticker.py
selfcord/store.py
selfcord/subscriptions.py
selfcord/team.py
selfcord/template.py
selfcord/threads.py
selfcord/tracking.py
selfcord/tutorial.py
selfcord/user.py
selfcord/utils.py
selfcord/voice_client.py
selfcord/voice_state.py
selfcord/welcome_screen.py
selfcord/widget.py
selfcord/bin/libopus-0.x64.dll
selfcord/bin/libopus-0.x86.dll
selfcord/ext/commands/__init__.py
selfcord/ext/commands/_types.py
selfcord/ext/commands/bot.py
selfcord/ext/commands/cog.py
selfcord/ext/commands/context.py
selfcord/ext/commands/converter.py
selfcord/ext/commands/cooldowns.py
selfcord/ext/commands/core.py
selfcordlibrary-1.0.0.dist-info/METADATA
selfcordlibrary-1.0.0.dist-info/WHEEL
selfcordlibrary-1.0.0.dist-info/RECORD
