Metadata-Version: 2.4
Name: selfcordLibrary
Version: 1.0.0
Summary: Updated selfcord library with bug fixes.
Author: Next
License: Unlicensed
Keywords: discord,selfbot,selfcord
Classifier: Operating System :: OS Independent
Classifier: Programming Language :: Python :: 3
Requires-Python: >=3.8
